balatromobile/__init__.py
balatromobile/__version__.py
balatromobile/gamble.py
balatromobile/patcher.py
balatromobile/resources.py
balatromobile/utils.py
balatromobile/artifacts/APKEditor-1.3.7.jar
balatromobile/artifacts/AndroidManifest.xml
balatromobile/artifacts/apksigner.jar
balatromobile/artifacts/love-11.5-SAF-android-embed.apk
balatromobile/artifacts/nunito-font.tty
balatromobile/artifacts/uber-debug.keystore
balatromobile/artifacts/zipalign-android-arm64
balatromobile/artifacts/zipalign-darwin-amd64
balatromobile/artifacts/zipalign-darwin-arm64
balatromobile/artifacts/zipalign-linux-amd64
balatromobile/artifacts/zipalign-linux-arm64
balatromobile/artifacts/zipalign-windows-amd64
balatromobile/artifacts/zipalign-windows-arm64
balatromobile/artifacts/res/drawable-hdpi/love.png
balatromobile/artifacts/res/drawable-mdpi/love.png
balatromobile/artifacts/res/drawable-xhdpi/love.png
balatromobile/artifacts/res/drawable-xxhdpi/love.png
balatromobile/artifacts/res/drawable-xxxhdpi/love.png
balatromobile/patches/basic.toml
balatromobile/patches/external-storage.toml
balatromobile/patches/fix-beta-langs.toml
balatromobile/patches/fps-settings.toml
balatromobile/patches/fps.toml
balatromobile/patches/landscape-hidpi.toml
balatromobile/patches/landscape.toml
balatromobile/patches/max-volume.toml
balatromobile/patches/no-background.toml
balatromobile/patches/no-crt.toml
balatromobile/patches/nunito-font.toml
balatromobile/patches/shaders-flames.toml
balatromobile/patches/simple-fx.toml
balatromobile/patches/square-display.toml
balatromobile-0.6.4.dist-info/entry_points.txt
balatromobile-0.6.4.dist-info/licenses/LICENSE.txt
balatromobile-0.6.4.dist-info/WHEEL
balatromobile-0.6.4.dist-info/METADATA
balatromobile-0.6.4.dist-info/RECORD
