Metadata-Version: 2.4
Name: balatromobile
Version: 0.6.4
Summary: balatromobile: build your mobile version of Balatro
Author-email: antipatico <code@bootkit.dev>
Requires-Python: >=3.11
Classifier: License :: OSI Approved :: MIT License
License-File: LICENSE.txt
Requires-Dist: tabulate
